mkrp/__init__.py
mkrp/cli.py
mkrp/modules/__init__.py
mkrp/modules/gitignore.py
mkrp/modules/license.py
mkrp/modules/settings.py
mkrp/modules/workflows.py
mkrp-0.1.0.dist-info/LICENSE
mkrp-0.1.0.dist-info/METADATA
mkrp-0.1.0.dist-info/WHEEL
mkrp-0.1.0.dist-info/entry_points.txt
mkrp-0.1.0.dist-info/RECORD
