Metadata-Version: 2.1
Name: mkrp
Version: 0.1.0
Summary:  A CLI to generate utils files for new projects.
Author: Henrique Sebastião
Author-email: contato@henriquesebastiao.com
Requires-Python: >=3.12,<4.0
Classifier: Development Status :: 5 - Production/Stable
Classifier: Intended Audience :: Developers
Classifier: Intended Audience :: Telecommunications Industry
Classifier: License :: OSI Approved :: MIT License
Classifier: Natural Language :: English
Classifier: Programming Language :: Python :: 3
Classifier: Programming Language :: Python :: 3.12
Classifier: Topic :: Software Development
Classifier: Topic :: Utilities
Requires-Dist: typer[all] (>=0.12.3,<0.13.0)
Project-URL: Bug Tracker, https://github.com/henriquesebastiao/mkrp/issues
Project-URL: Documentation, https://mkrp.henriquesebastiao.com
Project-URL: Homepage, https://mkrp.henriquesebastiao.com
Project-URL: Repository, https://github.com/henriquesebastiao/mkrp
